{
    "shagua": {
        "0": [
            0,
            0,
            0,
            0
        ],
        "1": [
            0,
            106532,
            75462,
            74859
        ],
        "2": [
            0,
            148804,
            110168,
            110098
        ],
        "3": [
            0,
            199147,
            155622,
            155182
        ],
        "4": [
            0,
            257176,
            208787,
            206674
        ],
        "5": [
            0,
            322265,
            269126,
            269039
        ]
    },
    "fujian": {
        "0": [
            0,
            0,
            0,
            0
        ],
        "1": [
            0,
            143198,
            102563,
            100911
        ],
        "2": [
            0,
            188331,
            140373,
            138581
        ],
        "3": [
            0,
            241769,
            186740,
            185181
        ],
        "4": [
            0,
            300910,
            241363,
            240182
        ],
        "5": [
            0,
            369250,
            302868,
            301294
        ]
    },
    "sichuan": {
        "0": [
            0,
            0,
            0,
            0
        ],
        "1": [
            0,
            117842,
            119312,
            115735
        ],
        "2": [
            0,
            208148,
            209619,
            207995
        ],
        "3": [
            0,
            321799,
            322591,
            324537
        ],
        "4": [
            0,
            463045,
            461131,
            467268
        ],
        "5": [
            0,
            630240,
            625931,
            634655
        ]
    }
}